jolescraper/JoleScraper.py
jolescraper/__init__.py
jolescraper-0.1.0.dist-info/METADATA
jolescraper-0.1.0.dist-info/WHEEL
jolescraper-0.1.0.dist-info/top_level.txt
jolescraper-0.1.0.dist-info/RECORD
